{
	"name": "Train-Tech-Fix",
	"version": "0.1.1",
	"title": "Train Technology Fix",
	"title_original": "Train Technology Fix",
	"author": "Anti-Antidote",
	"contact": "http://www.reddit.com/u/Anti-Antidote",
	"factorio_version": "0.13",
	"description": "Rebalances train technologies to include Cargo Wagons in the Railway technology. Credit goes to /u/bluewales73 for the idea.",
	"description_original": "Rebalances train technologies to include Cargo Wagons in the Railway technology. Credit goes to /u/bluewales73 for the idea."
}